RustXingnengShouceFix1/README.md
RustXingnengShouceFix1/__init__.py
RustXingnengShouceFix1/__main__.py
RustXingnengShouceFix1/file.epub
RustXingnengShouceFix1/index.html
RustXingnengShouceFix1/css/__init__.py
RustXingnengShouceFix1/css/annotations.css
RustXingnengShouceFix1/css/main.css
RustXingnengShouceFix1/css/normalize.css
RustXingnengShouceFix1/css/popup.css
RustXingnengShouceFix1/font/__init__.py
RustXingnengShouceFix1/font/fontello.eot
RustXingnengShouceFix1/font/fontello.svg
RustXingnengShouceFix1/font/fontello.ttf
RustXingnengShouceFix1/font/fontello.woff
RustXingnengShouceFix1/img/__init__.py
RustXingnengShouceFix1/img/annotator-glyph-sprite.png
RustXingnengShouceFix1/img/annotator-icon-sprite.png
RustXingnengShouceFix1/img/apple-touch-icon.png
RustXingnengShouceFix1/img/cancelfullscreen.png
RustXingnengShouceFix1/img/close.png
RustXingnengShouceFix1/img/fullscreen.png
RustXingnengShouceFix1/img/loader.gif
RustXingnengShouceFix1/img/menu-icon.png
RustXingnengShouceFix1/img/save.png
RustXingnengShouceFix1/img/saved.png
RustXingnengShouceFix1/img/settings-s.png
RustXingnengShouceFix1/img/settings.png
RustXingnengShouceFix1/img/star.png
RustXingnengShouceFix1/js/__init__.py
RustXingnengShouceFix1/js/epub.js
RustXingnengShouceFix1/js/epub.min.js
RustXingnengShouceFix1/js/epub.min.map
RustXingnengShouceFix1/js/hooks.min.js
RustXingnengShouceFix1/js/hooks.min.map
RustXingnengShouceFix1/js/reader.js
RustXingnengShouceFix1/js/reader.js.map
RustXingnengShouceFix1/js/reader.min.js
RustXingnengShouceFix1/js/reader.min.map
RustXingnengShouceFix1/js/hooks/__init__.py
RustXingnengShouceFix1/js/hooks/extensions/__init__.py
RustXingnengShouceFix1/js/hooks/extensions/highlight.js
RustXingnengShouceFix1/js/libs/__init__.py
RustXingnengShouceFix1/js/libs/jquery.min.js
RustXingnengShouceFix1/js/libs/localforage.min.js
RustXingnengShouceFix1/js/libs/screenfull.js
RustXingnengShouceFix1/js/libs/screenfull.min.js
RustXingnengShouceFix1/js/libs/zip.min.js
rust_xingneng_shouce_fix1-2025.3.25.1.dist-info/METADATA
rust_xingneng_shouce_fix1-2025.3.25.1.dist-info/WHEEL
rust_xingneng_shouce_fix1-2025.3.25.1.dist-info/entry_points.txt
rust_xingneng_shouce_fix1-2025.3.25.1.dist-info/top_level.txt
rust_xingneng_shouce_fix1-2025.3.25.1.dist-info/RECORD
